{"divisions":{"ocd-division/country:us":{"name":"United States","officeIndices":[0,1]},"ocd-division/country:us/state:ca":{"name":"California","officeIndices":[2,3,4,5,6,7,8,9,10,11]}},"kind":"civicinfo#representativeInfoResponse","normalizedInput":{"city":"","line1":"","state":"CA","zip":""},"offices":[{"divisionId":"ocd-division/country:us","levels":["country"],"name":"President of the United States","officialIndices":[0],"roles":["headOfState","headOfGovernment"]},{"divisionId":"ocd-division/country:us","levels":["country"],"name":"Vice President of the United States","officialIndices":[1],"roles":["deputyHeadOfGovernment"]},{"divisionId":"ocd-division/country:us/state:ca","levels":["country"],"name":"U.S. Senator","officialIndices":[2,3],"roles":["legislatorUpperBody"]},{"divisionId":"ocd-division/country:us/state:ca","levels":["administrativeArea1"],"name":"Governor of California","officialIndices":[4],"roles":["headOfGovernment"]},{"divisionId":"ocd-division/country:us/state:ca","levels":["administrativeArea1"],"name":"Lieutenant Governor of California","officialIndices":[5],"roles":["deputyHeadOfGovernment"]},{"divisionId":"ocd-division/country:us/state:ca","levels":["administrativeArea1"],"name":"CA State Treasurer","officialIndices":[6]},{"divisionId":"ocd-division/country:us/state:ca","levels":["administrativeArea1"],"name":"CA Attorney General","officialIndices":[7]},{"divisionId":"ocd-division/country:us/state:ca","levels":["administrativeArea1"],"name":"CA State Controller","officialIndices":[8]},{"divisionId":"ocd-division/country:us/state:ca","levels":["administrativeArea1"],"name":"CA Insurance Commissioner","officialIndices":[9]},{"divisionId":"ocd-division/country:us/state:ca","levels":["administrativeArea1"],"name":"CA Secretary of State","officialIndices":[10]},{"divisionId":"ocd-division/country:us/state:ca","levels":["administrativeArea1"],"name":"CA Supreme Court Justice","officialIndices":[11,12,13,14,15,16,17]},{"divisionId":"ocd-division/country:us/state:ca","levels":["administrativeArea1"],"name":"CA State Superintendent of Public Instruction","officialIndices":[18]}],"officials":[{"address":[{"city":"Washington","line1":"1600 Pennsylvania Avenue Northwest","state":"DC","zip":"20500"}],"channels":[{"id":"DonaldTrump","type":"Facebook"},{"id":"potus","type":"Twitter"},{"id":"whitehouse","type":"YouTube"}],"name":"Donald J. Trump","party":"Republican Party","phones":["(202) 456-1111"],"photoUrl":"https://www.whitehouse.gov/sites/whitehouse.gov/files/images/45/PE%20Color.jpg","urls":["https://www.whitehouse.gov/"]},{"address":[{"city":"Washington","line1":"1600 Pennsylvania Avenue Northwest","state":"DC","zip":"20500"}],"channels":[{"id":"mikepence","type":"Facebook"},{"id":"VP","type":"Twitter"}],"name":"Mike Pence","party":"Republican Party","phones":["(202) 456-1111"],"photoUrl":"https://www.whitehouse.gov/sites/whitehouse.gov/files/images/45/VPE%20Color.jpg","urls":["https://www.whitehouse.gov/"]},{"address":[{"city":"Washington","line1":"331 Hart Senate Office Building","state":"DC","zip":"20510"}],"channels":[{"id":"SenatorFeinstein","type":"Facebook"},{"id":"SenFeinstein","type":"Twitter"},{"id":"SenatorFeinstein","type":"YouTube"}],"name":"Dianne Feinstein","party":"Democratic Party","phones":["(202) 224-3841"],"photoUrl":"http://bioguide.congress.gov/bioguide/photo/F/F000062.jpg","urls":["https://www.feinstein.senate.gov/"]},{"address":[{"city":"Washington","line1":"112 Hart Senate Office Building","state":"DC","zip":"20510"}],"channels":[{"id":"KamalaHarris","type":"Facebook"},{"id":"KamalaHarris","type":"Twitter"},{"id":"UC0XBsJpPhOLg0k4x9ZwrWzw","type":"YouTube"}],"name":"Kamala D. Harris","party":"Democratic Party","phones":["(202) 224-3553"],"urls":["https://www.harris.senate.gov"]},{"address":[{"city":"Sacramento","line1":"1303 10th Street","state":"CA","zip":"95814"}],"channels":[{"id":"CAgovernor","type":"Facebook"},{"id":"CAgovernor","type":"Twitter"}],"name":"Gavin Newsom","party":"Democratic Party","phones":["(916) 445-2841"],"urls":["https://www.gov.ca.gov/"]},{"address":[{"city":"Sacramento","line1":"1315 10th Street","state":"CA","zip":"95814"}],"channels":[{"id":"EleniKounalakis","type":"Facebook"},{"id":"CALtGovernor","type":"Twitter"}],"name":"Eleni Kounalakis","party":"Democratic Party","phones":["(916) 445-8994"],"urls":["https://ltg.ca.gov/"]},{"address":[{"city":"Sacramento","line1":"915 Capitol Mall","state":"CA","zip":"95814"}],"channels":[{"id":"CaliforniaSTO","type":"Facebook"},{"id":"CalTreasurer","type":"Twitter"}],"name":"Fiona Ma","party":"Democratic Party","phones":["(916) 653-2995"],"urls":["https://www.treasurer.ca.gov/"]},{"channels":[{"id":"AGBecerra","type":"Facebook"},{"id":"AGBecerra","type":"Twitter"}],"name":"Xavier Becerra","party":"Democratic Party","phones":["(916) 445-9555"],"urls":["https://oag.ca.gov/"]},{"address":[{"city":"Sacramento","line1":"300 Capitol Mall","state":"CA","zip":"95814"}],"channels":[{"id":"California-State-Controllers-Office-137732083043662","type":"Facebook"},{"id":"CAController","type":"Twitter"}],"name":"Betty T. Yee","party":"Democratic Party","phones":["(916) 445-2636"],"urls":["https://www.sco.ca.gov/"]},{"address":[{"city":"Sacramento","line1":"300 Capitol Mall","state":"CA","zip":"95814"}],"channels":[{"id":"insurancecagov","type":"Facebook"},{"id":"ICRicardoLara","type":"Twitter"}],"name":"Ricardo Lara","party":"Democratic Party","phones":["(800) 927-4357"],"urls":["http://www.insurance.ca.gov/"]},{"address":[{"city":"Sacramento","line1":"1500 11th Street","state":"CA","zip":"95814"}],"channels":[{"id":"CaliforniaSOS","type":"Facebook"},{"id":"CASOSvote","type":"Twitter"}],"name":"Alex Padilla","party":"Democratic Party","phones":["(916) 653-6814"],"urls":["https://www.sos.ca.gov/"]},{"address":[{"city":"San Francisco","line1":"350 McAllister Street","state":"CA","zip":"94102"}],"channels":[{"id":"CalCourts","type":"Twitter"}],"name":"Carol A. Corrigan","party":"Nonpartisan","phones":["(415) 865-7000"],"urls":["https://www.courts.ca.gov/supremecourt.htm"]},{"address":[{"city":"San Francisco","line1":"350 McAllister Street","state":"CA","zip":"94102"}],"channels":[{"id":"CalCourts","type":"Twitter"}],"name":"Joshua P. Groban","party":"Nonpartisan","phones":["(415) 865-7000"],"urls":["https://www.courts.ca.gov/supremecourt.htm"]},{"address":[{"city":"San Francisco","line1":"350 McAllister Street","state":"CA","zip":"94102"}],"channels":[{"id":"CalCourts","type":"Twitter"}],"name":"Ming W. Chin","party":"Nonpartisan","phones":["(415) 865-7000"],"urls":["https://www.courts.ca.gov/supremecourt.htm"]},{"address":[{"city":"San Francisco","line1":"350 McAllister Street","state":"CA","zip":"94102"}],"channels":[{"id":"CalCourts","type":"Twitter"}],"name":"Goodwin H. Liu","party":"Nonpartisan","phones":["(415) 865-7000"],"urls":["https://www.courts.ca.gov/supremecourt.htm"]},{"address":[{"city":"San Francisco","line1":"350 McAllister Street","state":"CA","zip":"94102"}],"channels":[{"id":"CalCourts","type":"Twitter"}],"name":"Leondra R. Kruger","party":"Nonpartisan","phones":["(415) 865-7000"],"urls":["https://www.courts.ca.gov/supremecourt.htm"]},{"address":[{"city":"San Francisco","line1":"350 McAllister Street","state":"CA","zip":"94102"}],"channels":[{"id":"CalCourts","type":"Twitter"}],"name":"Tani G. Cantil-Sakauye","party":"Nonpartisan","phones":["(415) 865-7000"],"urls":["https://www.courts.ca.gov/supremecourt.htm"]},{"address":[{"city":"San Francisco","line1":"350 McAllister Street","state":"CA","zip":"94102"}],"channels":[{"id":"CalCourts","type":"Twitter"}],"name":"Mariano-Florentino Cuéllar","party":"Nonpartisan","phones":["(415) 865-7000"],"urls":["https://www.courts.ca.gov/supremecourt.htm"]},{"address":[{"city":"Sacramento","line1":"1430 N Street","state":"CA","zip":"95814"}],"channels":[{"id":"CAEducation","type":"Facebook"},{"id":"CADeptEd","type":"Twitter"}],"name":"Tony Thurmond","party":"Nonpartisan","phones":["(916) 319-0800"],"urls":["https://www.cde.ca.gov/eo/"]}]}
